invoice2data/__init__.py
invoice2data/main.py
invoice2data/extract/__init__.py
invoice2data/extract/invoice_template.py
invoice2data/extract/loader.py
invoice2data/extract/parsers/__init__.py
invoice2data/extract/parsers/__interface__.py
invoice2data/extract/parsers/lines.py
invoice2data/extract/parsers/regex.py
invoice2data/extract/parsers/static.py
invoice2data/extract/plugins/__init__.py
invoice2data/extract/plugins/__interface__.py
invoice2data/extract/plugins/lines.py
invoice2data/extract/plugins/tables.py
invoice2data/extract/templates/au/au.com.opal.yml
invoice2data/extract/templates/au/au.com.telstra.yml
invoice2data/extract/templates/be/be.accor.invest.ibis.yml
invoice2data/extract/templates/be/be.accor.invest.novotel.yml
invoice2data/extract/templates/be/be.boucherie.pochet.yml
invoice2data/extract/templates/be/be.cebeo.yml
invoice2data/extract/templates/be/be.eg_retail.yml
invoice2data/extract/templates/be/be.lampiris.facture-dacompte.yml
invoice2data/extract/templates/be/be.lampiris.factuur.yml
invoice2data/extract/templates/be/be.lampiris.regularisation.yml
invoice2data/extract/templates/be/be.melchior-vins.yml
invoice2data/extract/templates/be/be.proximus.yml
invoice2data/extract/templates/be/be.scarlet.yml
invoice2data/extract/templates/be/be.securex.social.yml
invoice2data/extract/templates/ch/ch.pcengines.yml
invoice2data/extract/templates/com/com.AzureInterior.yml
invoice2data/extract/templates/com/com.amazon.aws.yml
invoice2data/extract/templates/com/com.apple.yml
invoice2data/extract/templates/com/com.apps4rent.yml
invoice2data/extract/templates/com/com.binarylife.yml
invoice2data/extract/templates/com/com.bloomberg.yml
invoice2data/extract/templates/com/com.cloudns.yml
invoice2data/extract/templates/com/com.datadoghq.yml
invoice2data/extract/templates/com/com.digitalocean.yml
invoice2data/extract/templates/com/com.envato.yml
invoice2data/extract/templates/com/com.expressvpn.yml
invoice2data/extract/templates/com/com.expressvpn_prio6.yml
invoice2data-0.4.5.dist-info/METADATA
invoice2data-0.4.5.dist-info/WHEEL
invoice2data-0.4.5.dist-info/entry_points.txt
invoice2data-0.4.5.dist-info/top_level.txt
invoice2data-0.4.5.dist-info/RECORD
