Metadata-Version: 2.1
Name: invoice2data
Version: 0.4.5
Summary: Python parser to extract data from pdf invoice
Home-page: https://github.com/invoice-x/invoice2data
Author: Manuel Riel
License: MIT License
Keywords: pdf,invoicing
Classifier: Development Status :: 5 - Production/Stable
Classifier: Environment :: MacOS X
Classifier: Environment :: Console
Classifier: Environment :: Win32 (MS Windows)
Classifier: Operating System :: MacOS
Classifier: Operating System :: POSIX
Classifier: Operating System :: Unix
Classifier: Operating System :: Microsoft :: Windows
Classifier: License :: OSI Approved :: MIT License
Classifier: Programming Language :: Python :: 3.7
Classifier: Programming Language :: Python :: 3.8
Classifier: Programming Language :: Python :: 3.9
Classifier: Programming Language :: Python :: 3.10
Classifier: Programming Language :: Python :: 3.11
Classifier: Topic :: Office/Business :: Financial
Classifier: Topic :: Office/Business :: Financial :: Accounting
Requires-Dist: pillow
Requires-Dist: pyyaml
Requires-Dist: dateparser
Provides-Extra: test
Requires-Dist: pytest; extra == "test"
Requires-Dist: pytest-cov; extra == "test"
Requires-Dist: flake8; extra == "test"
Requires-Dist: pdfminer.six; extra == "test"
Requires-Dist: pdfplumber; extra == "test"
Requires-Dist: tox; extra == "test"
